opti_extensions/__init__.py
opti_extensions/_dict_mixins.py
opti_extensions/_index_sets.py
opti_extensions/_pandas_accessors.py
opti_extensions/_param_dicts.py
opti_extensions/_var_dict_base.py
opti_extensions/py.typed
opti_extensions/docplex/__init__.py
opti_extensions/docplex/_model_funcs.py
opti_extensions/docplex/_tuning_funcs.py
opti_extensions/docplex/_var_dicts.py
opti_extensions/docplex/_var_funcs.py
opti_extensions/gurobipy/__init__.py
opti_extensions/gurobipy/_var_dicts.py
opti_extensions/gurobipy/_var_funcs.py
opti_extensions/xpress/__init__.py
opti_extensions/xpress/_var_dicts.py
opti_extensions/xpress/_var_funcs.py
opti_extensions-1.2.0.dist-info/licenses/LICENSE
opti_extensions-1.2.0.dist-info/licenses/NOTICE
opti_extensions-1.2.0.dist-info/METADATA
opti_extensions-1.2.0.dist-info/WHEEL
opti_extensions-1.2.0.dist-info/top_level.txt
opti_extensions-1.2.0.dist-info/RECORD
