Metadata-Version: 2.4
Name: opti-extensions
Version: 1.2.0
Summary: A collection of custom data structures and user-friendly functions for mathematical optimization modeling with DOcplex, gurobipy, and Xpress.
Author-email: Samarth Mistry <samarth.mistry@gmail.com>
License-Expression: Apache-2.0
Project-URL: Homepage, https://opti-extensions.readthedocs.io/
Project-URL: Documentation, https://opti-extensions.readthedocs.io/en/stable/#documentation
Project-URL: Source code, https://github.com/samarthmistry/opti-extensions/tree/main/src/opti_extensions
Project-URL: Changelog, https://github.com/samarthmistry/opti-extensions/releases
Keywords: CPLEX,DOcplex,Gurobi,gurobipy,Xpress,linear programming,mixed integer programming,optimization model
Classifier: Development Status :: 5 - Production/Stable
Classifier: Intended Audience :: Developers
Classifier: Intended Audience :: Information Technology
Classifier: Intended Audience :: Science/Research
Classifier: Operating System :: OS Independent
Classifier: Programming Language :: Python
Classifier: Programming Language :: Python :: 3.10
Classifier: Programming Language :: Python :: 3.11
Classifier: Programming Language :: Python :: 3.12
Classifier: Programming Language :: Python :: 3.13
Classifier: Typing :: Typed
Requires-Python: >=3.10
License-File: LICENSE
License-File: NOTICE
Requires-Dist: typing_extensions>=4.10.0
Provides-Extra: solver-apis
Requires-Dist: cplex>=20.1.0.4; extra == "solver-apis"
Requires-Dist: docplex>=2.25.236; extra == "solver-apis"
Requires-Dist: gurobipy>=11.0.0; extra == "solver-apis"
Requires-Dist: xpress>=9.4.0; extra == "solver-apis"
Provides-Extra: tests
Requires-Dist: pytest>=8.1.1; extra == "tests"
Requires-Dist: coverage>=7.4.4; extra == "tests"
Requires-Dist: pytest-cov>=4.1.0; extra == "tests"
Requires-Dist: pytest-randomly>=3.15.0; extra == "tests"
Requires-Dist: mypy[faster-cache]<=1.15.0,>=1.13.0; extra == "tests"
Requires-Dist: pandas>=1.5.0; extra == "tests"
Requires-Dist: pandas-stubs>=1.5.0; extra == "tests"
Provides-Extra: docs
Requires-Dist: Sphinx==8.1.3; extra == "docs"
Requires-Dist: sphinx-autosummary-accessors==2025.3.1; extra == "docs"
Requires-Dist: ansys-sphinx-theme==1.4.5; extra == "docs"
Requires-Dist: sphinx_design==0.6.1; extra == "docs"
Requires-Dist: sphinx_gallery==0.19.0; extra == "docs"
Requires-Dist: sphinx-copybutton==0.5.2; extra == "docs"
Requires-Dist: sphinx-notfound-page==1.1.0; extra == "docs"
Requires-Dist: matplotlib==3.10.3; extra == "docs"
Requires-Dist: numpy<2.0; extra == "docs"
Requires-Dist: pandas>=1.5.0; extra == "docs"
Requires-Dist: pandas-stubs>=1.5.0; extra == "docs"
Requires-Dist: numpydoc==1.8.0; extra == "docs"
Provides-Extra: dev
Requires-Dist: ruff>=0.7.0; extra == "dev"
Requires-Dist: pre-commit>=3.8.0; extra == "dev"
Requires-Dist: tox>=4.14.1; extra == "dev"
Requires-Dist: opti-extensions[tests]; extra == "dev"
Requires-Dist: opti-extensions[docs]; extra == "dev"
Dynamic: license-file
